{
  "af": "Afrikaans",
  "sq": "Shqip",
  "am": "አማርኛ",
  "ar": "العربية",
  "hy": "Հայերեն",
  "az": "Azərbaycan",
  "eu": "Euskara",
  "be": "Беларуская",
  "bn": "বাংলা",
  "bs": "Bosanski",
  "bg": "Български",
  "ca": "Català",
  "ceb": "Cebuano",
  "ny": "Nyanca",
  "zh": "中文",
  "co": "Korsika",
  "hr": "Hrvatski",
  "cs": "Čeština",
  "da": "Dansk",
  "nl": "Nederlands",
  "en": "English",
  "eo": "Esperanto",
  "et": "Eesti",
  "fi": "Suomi",
  "fr": "Français",
  "fy": "Frysk",
  "gl": "Galego",
  "ka": "Ქართული",
  "de": "Deutsch",
  "el": "Ελληνικά",
  "gu": "ગુજરાતી",
  "ht": "Haiti kreol",
  "ha": "Hausa",
  "haw": "ʻŌlelo Hawaiʻi",
  "he": "עברית",
  "hi": "हिन्दी",
  "hmn": "Monq",
  "hu": "Magyar",
  "is": "Íslenska",
  "ig": "Igbo",
  "id": "Indonesia",
  "ga": "Gaeilge",
  "it": "Italiano",
  "ja": "日本語",
  "jv": "Jawa",
  "kn": "ಕನ್ನಡ",
  "kk": "Қазақ тілі",
  "km": "ខ្មែរ",
  "rw": "Ikinyarwanda",
  "ko": "한국어",
  "ku": "Kurdî (kurmancî)",
  "ky": "Кыргызча",
  "lo": "ລາວ",
  "la": "Latın",
  "lv": "Latviešu",
  "lt": "Lietuvių",
  "lb": "Lëtzebuergesch",
  "mk": "Македонски",
  "mg": "Malagasy",
  "ms": "Melayu",
  "ml": "മലയാളം",
  "mt": "Malti",
  "mi": "Māori",
  "mr": "मराठी",
  "mn": "Монгол",
  "my": "မြန်မာ",
  "ne": "नेपाली",
  "no": "Norsk",
  "or": "ଓଡ଼ିଆ",
  "ps": "پښتو",
  "fa": "فارسی",
  "pl": "Polski",
  "pt": "Português",
  "pa": "ਪੰਜਾਬੀ",
  "ro": "Română",
  "ru": "Русский",
  "sm": "Samoa",
  "gd": "Gàidhlig",
  "sr": "Српски",
  "st": "Sesotho",
  "sn": "ChiShona",
  "sd": "سنڌي",
  "si": "සිංහල",
  "sk": "Slovenčina",
  "sl": "Slovenščina",
  "so": "Soomaali",
  "es": "Español",
  "su": "Basa Sunda",
  "sw": "Kiswahili",
  "sv": "Svenska",
  "tl": "Filipino",
  "ta": "தமிழ்",
  "tt": "Татар",
  "te": "తెలుగు",
  "th": "ไทย",
  "tr": "Türkçe",
  "tk": "Türkmen dili",
  "uk": "Українська",
  "ur": "اردو",
  "ug": "ئۇيغۇرچە",
  "uz": "O‘zbek",
  "vi": "Tiếng Việt",
  "cy": "Cymraeg",
  "xh": "IsiXhosa",
  "yi": "ייִדיש",
  "yo": "Èdè Yorùbá",
  "zu": "IsiZulu"
}